python_orb_slam3/__init__.py
orb_slam3.cpython-311-darwin.so
python_orb_slam3-0.1.1.dist-info/LICENSE
python_orb_slam3-0.1.1.dist-info/METADATA
python_orb_slam3-0.1.1.dist-info/WHEEL
python_orb_slam3-0.1.1.dist-info/RECORD
