Metadata-Version: 2.1
Name: python-orb-slam3
Version: 0.1.1
Summary: A Python wrapper of ORB-SLAM3 algorithm
License: GPL-3.0
Author: Mix
Author-email: 32300164+mnixry@users.noreply.github.com
Requires-Python: >=3.8,<4.0
Classifier: License :: OSI Approved :: GNU General Public License v3 (GPLv3)
Classifier: Programming Language :: Python :: 3
Classifier: Programming Language :: Python :: 3.8
Classifier: Programming Language :: Python :: 3.9
Classifier: Programming Language :: Python :: 3.10
Classifier: Programming Language :: Python :: 3.11
Classifier: Programming Language :: Python :: 3.12
Requires-Dist: numpy (>=1.20.0,<2.0.0)
Requires-Dist: opencv-python (>=4,<5)
